araxia/__init__.py
araxia/forecast.py
araxia/network.py
araxia/train.py
araxia/utils.py
araxia/preprocessing/__init__.py
araxia/preprocessing/cyclic.py
araxia/preprocessing/date_features.py
araxia/preprocessing/lagged.py
araxia/preprocessing/onehot_dow.py
araxia-0.2.0.dist-info/licenses/LICENSE
araxia-0.2.0.dist-info/METADATA
araxia-0.2.0.dist-info/WHEEL
araxia-0.2.0.dist-info/top_level.txt
araxia-0.2.0.dist-info/RECORD
