Metadata-Version: 2.4
Name: araxia
Version: 0.2.0
Summary: A minimal neural network library built from scratch for time series forecasting and analysis.
Home-page: https://github.com/C5m7b4/Araxia
Author: C5m7b4
Author-email: Mike <mike@example.com>
License: MIT
Project-URL: Homepage, https://github.com/yourusername/araxia
Requires-Python: >=3.7
License-File: LICENSE
Requires-Dist: numpy
Dynamic: author
Dynamic: home-page
Dynamic: license-file
Dynamic: requires-python
